smart_fruit/__init__.py
smart_fruit/feature_class.py
smart_fruit/model.py
smart_fruit/model_selection.py
smart_fruit/utils.py
smart_fruit/feature_types/__init__.py
smart_fruit/feature_types/compound_types.py
smart_fruit/feature_types/feature_type_base.py
smart_fruit/feature_types/simple_types.py
smart_fruit-1.2.1.dist-info/DESCRIPTION.rst
smart_fruit-1.2.1.dist-info/METADATA
smart_fruit-1.2.1.dist-info/RECORD
smart_fruit-1.2.1.dist-info/WHEEL
smart_fruit-1.2.1.dist-info/metadata.json
smart_fruit-1.2.1.dist-info/top_level.txt
