Metadata-Version: 2.0
Name: smart-fruit
Version: 1.2.1
Summary: A Python schema-based machine learning library
Home-page: https://github.com/madman-bob/Smart-Fruit
Author: Robert Wright
Author-email: madman.bob@hotmail.co.uk
License: MIT
Platform: UNKNOWN
Classifier: License :: OSI Approved :: MIT License
Classifier: Programming Language :: Python :: 3
Classifier: Programming Language :: Python :: 3.6
Classifier: Programming Language :: Python :: 3.7
Classifier: Programming Language :: Python :: 3 :: Only
Requires-Dist: pandas
Requires-Dist: scikit-learn
Requires-Dist: scipy
